vepar.py
vepar-2.5.dist-info/WHEEL
vepar-2.5.dist-info/METADATA
vepar-2.5.dist-info/RECORD
