Metadata-Version: 2.1
Name: vepar
Version: 2.5
Summary: Leksička, sintaksna, semantička analiza te izvođenje programa.
Home-page: https://web.math.pmf.unizg.hr/~veky/
Author: Veky
Author-email: veky@math.hr
